RefactoringguruShejimoshi/README.md
RefactoringguruShejimoshi/__init__.py
RefactoringguruShejimoshi/__main__.py
RefactoringguruShejimoshi/file.epub
RefactoringguruShejimoshi/index.html
RefactoringguruShejimoshi/css/__init__.py
RefactoringguruShejimoshi/css/annotations.css
RefactoringguruShejimoshi/css/main.css
RefactoringguruShejimoshi/css/normalize.css
RefactoringguruShejimoshi/css/popup.css
RefactoringguruShejimoshi/font/__init__.py
RefactoringguruShejimoshi/font/fontello.eot
RefactoringguruShejimoshi/font/fontello.svg
RefactoringguruShejimoshi/font/fontello.ttf
RefactoringguruShejimoshi/font/fontello.woff
RefactoringguruShejimoshi/img/__init__.py
RefactoringguruShejimoshi/img/annotator-glyph-sprite.png
RefactoringguruShejimoshi/img/annotator-icon-sprite.png
RefactoringguruShejimoshi/img/apple-touch-icon.png
RefactoringguruShejimoshi/img/cancelfullscreen.png
RefactoringguruShejimoshi/img/close.png
RefactoringguruShejimoshi/img/fullscreen.png
RefactoringguruShejimoshi/img/loader.gif
RefactoringguruShejimoshi/img/menu-icon.png
RefactoringguruShejimoshi/img/save.png
RefactoringguruShejimoshi/img/saved.png
RefactoringguruShejimoshi/img/settings-s.png
RefactoringguruShejimoshi/img/settings.png
RefactoringguruShejimoshi/img/star.png
RefactoringguruShejimoshi/js/__init__.py
RefactoringguruShejimoshi/js/epub.js
RefactoringguruShejimoshi/js/epub.min.js
RefactoringguruShejimoshi/js/epub.min.map
RefactoringguruShejimoshi/js/hooks.min.js
RefactoringguruShejimoshi/js/hooks.min.map
RefactoringguruShejimoshi/js/reader.js
RefactoringguruShejimoshi/js/reader.js.map
RefactoringguruShejimoshi/js/reader.min.js
RefactoringguruShejimoshi/js/reader.min.map
RefactoringguruShejimoshi/js/hooks/__init__.py
RefactoringguruShejimoshi/js/hooks/extensions/__init__.py
RefactoringguruShejimoshi/js/hooks/extensions/highlight.js
RefactoringguruShejimoshi/js/libs/__init__.py
RefactoringguruShejimoshi/js/libs/jquery.min.js
RefactoringguruShejimoshi/js/libs/localforage.min.js
refactoringguru_shejimoshi-2024.3.5.0.dist-info/METADATA
refactoringguru_shejimoshi-2024.3.5.0.dist-info/WHEEL
refactoringguru_shejimoshi-2024.3.5.0.dist-info/entry_points.txt
refactoringguru_shejimoshi-2024.3.5.0.dist-info/top_level.txt
refactoringguru_shejimoshi-2024.3.5.0.dist-info/RECORD
